gathering_task/__init__.py
gathering_task/task_runner.py
gathering_task/utils.py
gathering_task-0.3.0.dist-info/LICENSE
gathering_task-0.3.0.dist-info/METADATA
gathering_task-0.3.0.dist-info/WHEEL
gathering_task-0.3.0.dist-info/top_level.txt
gathering_task-0.3.0.dist-info/RECORD
