Metadata-Version: 2.1
Name: gathering-task
Version: 0.3.0
Summary: Gathering skeleton code...
Author-email: DDGG <ddcatgg@gmail.com>
License: MIT License        
Project-URL: Homepage, https://github.com/ddcatgg/gathering_task
Project-URL: Bug Tracker, https://github.com/ddcatgg/gathering_task/issues
Keywords: task,gathering
Classifier: Programming Language :: Python :: 3
Classifier: License :: OSI Approved :: MIT License
Classifier: Operating System :: OS Independent
Requires-Python: >=3.7
License-File: LICENSE
Requires-Dist: tqdm
